{"name":"build-javascript","namedChunkGroups":{"app":{"name":"app","assets":[{"name":"webpack-runtime-17a4234b30f392c1a084.js","size":4739},{"name":"framework-d68bba56a35053cd3932.js","size":140373},{"name":"app-9ae72498174647dd02eb.js","size":64983}],"filteredAssets":0,"assetsSize":210095,"filteredAuxiliaryAssets":3,"auxiliaryAssetsSize":603403},"component---src-pages-404-js":{"name":"component---src-pages-404-js","assets":[{"name":"styles.61979b68a6ef2d9291d6.css","size":9764},{"name":"component---src-pages-404-js-27e6bd307dee930ec146.js","size":1791}],"filteredAssets":0,"assetsSize":11555,"filteredAuxiliaryAssets":1,"auxiliaryAssetsSize":4962},"component---src-pages-chat-js":{"name":"component---src-pages-chat-js","assets":[{"name":"styles.61979b68a6ef2d9291d6.css","size":9764},{"name":"component---src-pages-chat-js-afb630bdd6e1f8d95780.js","size":988443}],"filteredAssets":0,"assetsSize":998207,"filteredAuxiliaryAssets":1,"auxiliaryAssetsSize":2165506},"component---src-pages-index-js":{"name":"component---src-pages-index-js","assets":[{"name":"styles.61979b68a6ef2d9291d6.css","size":9764},{"name":"component---src-pages-index-js-bd8d993764d11bd2fe71.js","size":7639}],"filteredAssets":0,"assetsSize":17403,"filteredAuxiliaryAssets":1,"auxiliaryAssetsSize":17953}},"assetsByChunkName":{"app":["webpack-runtime-17a4234b30f392c1a084.js","framework-d68bba56a35053cd3932.js","app-9ae72498174647dd02eb.js"],"component---src-pages-404-js":["styles.61979b68a6ef2d9291d6.css","component---src-pages-404-js-27e6bd307dee930ec146.js"],"component---src-pages-chat-js":["styles.61979b68a6ef2d9291d6.css","component---src-pages-chat-js-afb630bdd6e1f8d95780.js"],"component---src-pages-index-js":["styles.61979b68a6ef2d9291d6.css","component---src-pages-index-js-bd8d993764d11bd2fe71.js"]},"childAssetsByChunkName":{}}