{
    "files": {
        "/dark.css": {
            "type": "text/css",
            "path": "dark.css"
        },
        "/darkn.css": {
            "type": "text/css",
            "path": "darkn.css"
        },
        "/lightn.css": {
            "type": "text/css",
            "path": "lightn.css"
        },
        "/light.css": {
            "type": "text/css",
            "path": "light.css"
        },
        "/loadingScreen.css": {
            "type": "text/css",
            "path": "loadingScreen.css"
        },
        "/index.js": {
            "type": "application/javascript",
            "path": "index.js"
        },
        "/chat.js": {
            "type": "application/javascript",
            "path": "chat.js"
        },
        "/mdpage.js": {
            "type": "application/javascript",
            "path": "mdpage.js"
        },
        "/index.html": {
            "type": "text/html",
            "path": "index.html"
        },
        "/chat.html": {
            "type": "text/html",
            "path": "chat.html"
        },
        "/.html": {
            "type": "text/html",
            "path": "index.html"
        },
        "/tos.html": {
            "type": "text/html",
            "path": "mdpage.html"
        },
        "/carp.html": {
            "type": "text/html",
            "path": "mdpage.html"
        },
        "/carp.md": {
            "type": "text/markdown",
            "path": "carp.md"
        },
        "/tos.md": {
            "type": "text/markdown",
            "path": "tos.md"
        },
        "/index.md": {
            "type": "text/markdown",
            "path": "index.md"
        },
        "/.md": {
            "type": "text/markdown",
            "path": "index.md"
        },
        "/icon.png": {
            "type": "image/png",
            "path": "icon.png"
        },
        "/swim1.png": {
            "type": "image/png",
            "path": "swim1.png"
        },
        "/nitro.png": {
            "type": "image/png",
            "path": "nitro.png"
        },
        "/login.html": {
            "type": "text/html",
            "path": "login.html"
        },
        "/disc.html": {
            "type": "text/html",
            "path": "disc.html"
        },
        "/google148b32a3196ad8a2.html": {
            "type": "text/html",
            "path": "google148b32a3196ad8a2.html"
        },
        "/chausdhsa89h98q3haiderhjka.html": {
            "type": "text/html",
            "path": "chausdhsa89h98q3haiderhjka.html"
        },
        "/LICENSE.txt": {
            "type": "text/plain",
            "path": "LICENSE"
        }
    }
}
